odoo8_addon_invoice_comment_template-8.0.1.0.0.99.dev19-py2.7-nspkg.pth
odoo8_addon_invoice_comment_template-8.0.1.0.0.99.dev19.dist-info/METADATA
odoo8_addon_invoice_comment_template-8.0.1.0.0.99.dev19.dist-info/RECORD
odoo8_addon_invoice_comment_template-8.0.1.0.0.99.dev19.dist-info/WHEEL
odoo8_addon_invoice_comment_template-8.0.1.0.0.99.dev19.dist-info/namespace_packages.txt
odoo8_addon_invoice_comment_template-8.0.1.0.0.99.dev19.dist-info/top_level.txt
odoo_addons/invoice_comment_template/README.rst
odoo_addons/invoice_comment_template/__init__.py
odoo_addons/invoice_comment_template/__openerp__.py
odoo_addons/invoice_comment_template/account_invoice.py
odoo_addons/invoice_comment_template/account_invoice_view.xml
odoo_addons/invoice_comment_template/base_comment_template_view.xml
odoo_addons/invoice_comment_template/i18n/ar.po
odoo_addons/invoice_comment_template/i18n/bg.po
odoo_addons/invoice_comment_template/i18n/bs.po
odoo_addons/invoice_comment_template/i18n/ca.po
odoo_addons/invoice_comment_template/i18n/cs.po
odoo_addons/invoice_comment_template/i18n/de.po
odoo_addons/invoice_comment_template/i18n/el_GR.po
odoo_addons/invoice_comment_template/i18n/en_GB.po
odoo_addons/invoice_comment_template/i18n/es.po
odoo_addons/invoice_comment_template/i18n/es_CR.po
odoo_addons/invoice_comment_template/i18n/es_EC.po
odoo_addons/invoice_comment_template/i18n/es_MX.po
odoo_addons/invoice_comment_template/i18n/es_PE.po
odoo_addons/invoice_comment_template/i18n/et.po
odoo_addons/invoice_comment_template/i18n/fi.po
odoo_addons/invoice_comment_template/i18n/fr.po
odoo_addons/invoice_comment_template/i18n/fr_CA.po
odoo_addons/invoice_comment_template/i18n/fr_CH.po
odoo_addons/invoice_comment_template/i18n/gl.po
odoo_addons/invoice_comment_template/i18n/hr.po
odoo_addons/invoice_comment_template/i18n/hr_HR.po
odoo_addons/invoice_comment_template/i18n/hu.po
odoo_addons/invoice_comment_template/i18n/id.po
odoo_addons/invoice_comment_template/i18n/invoice_comment_template.pot
odoo_addons/invoice_comment_template/i18n/it.po
odoo_addons/invoice_comment_template/i18n/ja.po
odoo_addons/invoice_comment_template/i18n/lt.po
odoo_addons/invoice_comment_template/i18n/mk.po
odoo_addons/invoice_comment_template/i18n/mn.po
odoo_addons/invoice_comment_template/i18n/nb.po
odoo_addons/invoice_comment_template/i18n/nb_NO.po
